airflow_mcp/__init__.py
airflow_mcp/airflow_mcp.py
airflow_mcp-0.1.1.dist-info/METADATA
airflow_mcp-0.1.1.dist-info/WHEEL
airflow_mcp-0.1.1.dist-info/entry_points.txt
airflow_mcp-0.1.1.dist-info/licenses/LICENSE
airflow_mcp-0.1.1.dist-info/RECORD
