Metadata-Version: 2.4
Name: airflow-mcp
Version: 0.1.1
Summary: 本项目是一个与 Apache Airflow 集成的 Model Context Protocol (MCP) 服务器，提供多种工具来管理和监控 Airflow 的 DAG 运行。它支持触发 DAG、获取 DAG 状态、回填数据、获取日志等操作。
Author-email: treerootboy <treerootboy@gmail.com>
License: MIT
License-File: LICENSE
Keywords: airflow,cli,management,mcp,monitoring,server
Requires-Python: >=3.12
Requires-Dist: httpx>=0.28.1
Requires-Dist: mcp[cli]>=1.5.0
